denetcdf/__init__.py
denetcdf/denetcdf.py
denetcdf-0.0.1.dist-info/LICENSE
denetcdf-0.0.1.dist-info/METADATA
denetcdf-0.0.1.dist-info/WHEEL
denetcdf-0.0.1.dist-info/top_level.txt
denetcdf-0.0.1.dist-info/RECORD
